lib_caida_collector/__init__.py
lib_caida_collector/__main__.py
lib_caida_collector/base_as.py
lib_caida_collector/bgp_dag.py
lib_caida_collector/caida_collector.py
lib_caida_collector/customer_provider_link.py
lib_caida_collector/link.py
lib_caida_collector/peer_link.py
lib_caida_collector/tests/__init__.py
lib_caida_collector-0.0.2.dist-info/LICENSE
lib_caida_collector-0.0.2.dist-info/METADATA
lib_caida_collector-0.0.2.dist-info/WHEEL
lib_caida_collector-0.0.2.dist-info/entry_points.txt
lib_caida_collector-0.0.2.dist-info/top_level.txt
lib_caida_collector-0.0.2.dist-info/RECORD
